{"web":{"client_id":"611883962059-hvgdcvt2firie3jscj1p3bkoekluvlkr.apps.googleusercontent.com","project_id":"gen-lang-client-0442564269","auth_uri":"https://accounts.google.com/o/oauth2/auth","token_uri":"https://oauth2.googleapis.com/token","auth_provider_x509_cert_url":"https://www.googleapis.com/oauth2/v1/certs","client_secret":"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","redirect_uris":["https://5173-idx-operx-1716732653613.cluster-y34ecccqenfhcuavp7vbnxv7zk.cloudworkstations.dev/dashboard"],"javascript_origins":["https://5173-idx-operx-1716732653613.cluster-y34ecccqenfhcuavp7vbnxv7zk.cloudworkstations.dev"]}}